qiangl/env.py
qiangl/logger.py
qiangl/example/__init__.py
qiangl/example/add.py
qiangl-0.0.6.dist-info/METADATA
qiangl-0.0.6.dist-info/WHEEL
qiangl-0.0.6.dist-info/licenses/LICENSE
qiangl-0.0.6.dist-info/RECORD
