Metadata-Version: 2.1
Name: qiangl
Version: 0.0.6
Summary: test!
Project-URL: Homepage, https://github.com/893379029/qiangl
Author-email: QIANGL <893379029@qq.com>
License: MIT License
License-File: LICENSE
Classifier: License :: OSI Approved :: MIT License
Classifier: Operating System :: OS Independent
Classifier: Programming Language :: Python :: 3
Requires-Python: >=3.7
